{
  "unversionedId": "API/signs-out-the-current-user",
  "id": "API/signs-out-the-current-user",
  "title": "Signs out the current user",
  "description": "This action can be performed by any authorized user. Once successfull the session cookie will be removed",
  "source": "@site/docs/API/signs-out-the-current-user.api.mdx",
  "sourceDirName": "API",
  "slug": "/API/signs-out-the-current-user",
  "permalink": "/OpenLeakedDocs/docs/API/signs-out-the-current-user",
  "draft": false,
  "editUrl": null,
  "tags": [],
  "version": "current",
  "frontMatter": {
    "id": "signs-out-the-current-user",
    "title": "Signs out the current user",
    "description": "This action can be performed by any authorized user. Once successfull the session cookie will be removed",
    "sidebar_label": "Signs out the current user",
    "hide_title": true,
    "hide_table_of_contents": true,
    "api": {
      "tags": [
        "authorisations"
      ],
      "description": "This action can be performed by any authorized user. Once successfull the session cookie will be removed",
      "responses": {
        "200": {
          "description": "Successfully signed out current user"
        },
        "401": {
          "description": "Could not end session for current user",
          "headers": {
            "X-CUSTOM-AUTHENTICATE": {
              "style": "simple",
              "explode": false,
              "schema": {
                "type": "string"
              }
            }
          }
        }
      },
      "security": [
        {
          "basicAuth": []
        }
      ],
      "method": "post",
      "path": "/api/auth/logout",
      "servers": [
        {
          "url": "https://virtserver.swaggerhub.com/Peetzie/OpenLeaked/1.7.1",
          "description": "SwaggerHub API Auto Mocking"
        },
        {
          "url": "localhost",
          "description": "Local running server"
        },
        {
          "url": "open-leaked.compute.dtu.dk",
          "description": "DTU Compute VPN Required"
        }
      ],
      "securitySchemes": {
        "basicAuth": {
          "type": "http",
          "scheme": "basic"
        }
      },
      "info": {
        "title": "Open Leaked YAML",
        "description": "## Introduction\nThis API is documented in **OpenAPI** format. \n\n## OpenAPI Specification\nThis API is documented in **OpenAPI format** and is based on\n[Petstore sample](http://petstore.swagger.io/) provided by [swagger.io](http://swagger.io) team.\n\n## Authentication\nThe application makes uses of build in authentication. Some of the client calls will be restricted. Use the HTTP basic form to authorize. ",
        "contact": {
          "name": "Open Leaked",
          "url": "https://github.com/Open-Leaked/Monorepo",
          "email": "openleaked@gmail.com"
        },
        "license": {
          "name": "Apache 2.0",
          "url": "http://www.apache.org/licenses/LICENSE-2.0.html"
        },
        "version": "2.0.1",
        "x-logo": {
          "url": "https://raw.githubusercontent.com/Open-Leaked/Monorepo/main/Assets/logo/png/logo-white.png?token=GHSAT0AAAAAACB2FNOUZBLHC6LN6IMED47EZC3SB3Q",
          "altText": "Open-Leaked Logo"
        }
      },
      "postman": {
        "name": "Signs out the current user",
        "description": {
          "content": "This action can be performed by any authorized user. Once successfull the session cookie will be removed",
          "type": "text/plain"
        },
        "url": {
          "path": [
            "api",
            "auth",
            "logout"
          ],
          "host": [
            "{{baseUrl}}"
          ],
          "query": [],
          "variable": []
        },
        "method": "POST",
        "auth": {
          "type": "basic",
          "basic": [
            {
              "type": "any",
              "value": "<Basic Auth Username>",
              "key": "username"
            },
            {
              "type": "any",
              "value": "<Basic Auth Password>",
              "key": "password"
            }
          ]
        }
      }
    },
    "sidebar_class_name": "post api-method",
    "info_path": "docs/API/open-leaked-yaml",
    "custom_edit_url": null
  },
  "sidebar": "openApiSidebar",
  "previous": {
    "title": "Authorise an existing user",
    "permalink": "/OpenLeakedDocs/docs/API/authorise-an-existing-user"
  },
  "next": {
    "title": "Verify user",
    "permalink": "/OpenLeakedDocs/docs/API/verify-user"
  }
}